number2word/__init__.py
number2word-0.0.1.dist-info/METADATA
number2word-0.0.1.dist-info/WHEEL
number2word-0.0.1.dist-info/top_level.txt
number2word-0.0.1.dist-info/RECORD
