Metadata-Version: 2.1
Name: number2word
Version: 0.0.1
Summary: A simple library for converting numbers to English words
Home-page: UNKNOWN
Author: Harry
Author-email: UNKNOWN
License: UNKNOWN
Platform: UNKNOWN
